ffi_navigator/__init__.py
ffi_navigator/import_resolver.py
ffi_navigator/langserver.py
ffi_navigator/lsp.py
ffi_navigator/pattern.py
ffi_navigator/util.py
ffi_navigator/workspace.py
ffi_navigator/dialect/__init__.py
ffi_navigator/dialect/base_provider.py
ffi_navigator/dialect/dgl.py
ffi_navigator/dialect/mxnet.py
ffi_navigator/dialect/taichi.py
ffi_navigator/dialect/torch.py
ffi_navigator/dialect/tvm.py
ffi_navigator-0.5.2.dist-info/DESCRIPTION.rst
ffi_navigator-0.5.2.dist-info/METADATA
ffi_navigator-0.5.2.dist-info/RECORD
ffi_navigator-0.5.2.dist-info/WHEEL
ffi_navigator-0.5.2.dist-info/metadata.json
ffi_navigator-0.5.2.dist-info/top_level.txt
