Metadata-Version: 2.0
Name: ffi-navigator
Version: 0.5.2
Summary: Language server for navigating FFI calls
Home-page: https://github.com/tqchen/ffi-navigator
Author: FFI navigator contributors
Author-email: tianqi.tchen@gmail.com
License: Apache-2.0
Platform: UNKNOWN
Classifier: Development Status :: 3 - Alpha
Classifier: Intended Audience :: Developers
Classifier: Topic :: Software Development :: Build Tools
Classifier: License :: OSI Approved :: Apache Software License
Classifier: Programming Language :: Python :: 3
Classifier: Programming Language :: Python :: 3.6
Requires-Dist: python-jsonrpc-server
Requires-Dist: attrs
